QieyunEncoder/__init__.py
QieyunEncoder/_母對應的標準等.py
QieyunEncoder/常量.py
QieyunEncoder/音韻地位.py
QieyunEncoder/韻鏡位置.py
QieyunEncoder/工具/__init__.py
QieyunEncoder/工具/反切.py
QieyunEncoder/工具/音韻地位到韻鏡位置.py
QieyunEncoder/工具/音韻屬性到韻鏡位置們.py
QieyunEncoder/工具/韻鏡位置到音韻地位.py
QieyunEncoder/轉換/__init__.py
QieyunEncoder/轉換/母到清濁.py
QieyunEncoder/轉換/母到組.py
QieyunEncoder/轉換/母到音.py
QieyunEncoder/轉換/母與等到類.py
QieyunEncoder/轉換/韻到攝.py
QieyunEncoder/轉換/韻目到韻.py
qieyun_encoder-0.5.0.dist-info/LICENSE
qieyun_encoder-0.5.0.dist-info/METADATA
qieyun_encoder-0.5.0.dist-info/WHEEL
qieyun_encoder-0.5.0.dist-info/top_level.txt
qieyun_encoder-0.5.0.dist-info/RECORD
